pytasknc/__init__.py
pytasknc/__main__.py
pytasknc/actions.py
pytasknc/config.py
pytasknc/draw.py
pytasknc/grid.py
pytasknc/models.py
pytasknc/taskw.py
pytasknc-0.1.2.dist-info/DESCRIPTION.rst
pytasknc-0.1.2.dist-info/METADATA
pytasknc-0.1.2.dist-info/RECORD
pytasknc-0.1.2.dist-info/WHEEL
pytasknc-0.1.2.dist-info/entry_points.txt
pytasknc-0.1.2.dist-info/metadata.json
pytasknc-0.1.2.dist-info/top_level.txt
