Metadata-Version: 2.0
Name: pytasknc
Version: 0.1.2
Summary: NCurses for TaskWarrior
Home-page: https://github.com/b-ryan/tasknc-python
Author: Buck Ryan
Author-email: UNKNOWN
License: UNKNOWN
Platform: UNKNOWN
Classifier: Programming Language :: Python :: 3 :: Only
Requires-Dist: PyYAML (<=4,>3)
